KMB/__init___.py
KMB/error.py
KMB/eta.py
KMB/route.py
KMB/stop.py
TransportationHK-0.0.0b1.dist-info/METADATA
TransportationHK-0.0.0b1.dist-info/WHEEL
TransportationHK-0.0.0b1.dist-info/top_level.txt
TransportationHK-0.0.0b1.dist-info/RECORD
