Metadata-Version: 2.1
Name: TransportationHK
Version: 0.0.0b1
Summary: The python package(pypi) about Hong Kong's transportation.
Home-page: https://github.com/max-github110331/TransportationHK/
Author: MaxPython110331
License: MIT
Classifier: Programming Language :: Python :: 3
Classifier: License :: OSI Approved :: MIT License
Classifier: Operating System :: OS Independent
Requires-Python: >=3.7
Requires-Dist: requests
